LICENSE
MANIFEST.in
README.md
setup.cfg
setup.py
src/constrained_decoding/__init__.py
src/constrained_decoding/dfa.py
src/constrained_decoding/version.txt
src/constrained_decoding.egg-info/PKG-INFO
src/constrained_decoding.egg-info/SOURCES.txt
src/constrained_decoding.egg-info/dependency_links.txt
src/constrained_decoding.egg-info/requires.txt
src/constrained_decoding.egg-info/top_level.txt
src/constrained_decoding/autoregressive_dfa_constraining/__init__.py
src/constrained_decoding/autoregressive_dfa_constraining/api.py
src/constrained_decoding/autoregressive_dfa_constraining/dfa_constrained_beam_search.py
src/constrained_decoding/autoregressive_dfa_constraining/dfa_constrained_generate.py
src/constrained_decoding/logits_processors/__init__.py
src/constrained_decoding/logits_processors/dfa_decoding.py
src/constrained_decoding/logits_processors/sequences_constraints.py
src/constrained_decoding/logits_processors/sequential_conditions.py
src/constrained_decoding/logits_processors/set_decoding.py
src/constrained_decoding/logits_processors/word_list_decoding.py
src/constrained_decoding/qasrl/__init__.py
src/constrained_decoding/qasrl/qasrl.py
src/constrained_decoding/qasrl/data/qasrl_slots.json