Metadata-Version: 2.1
Name: constrained-decoding
Version: 0.1.0
Summary: package for constrained text generation during decoding
Home-page: https://github.com/kleinay/seq2seq_constrained_decoding
Author: Ayal Klein
Author-email: ayal.s.klein@gmail.com
Classifier: Programming Language :: Python :: 3
Classifier: License :: OSI Approved :: MIT License
Classifier: Operating System :: OS Independent
Requires-Python: >=3.7
License-File: LICENSE
